dubbo_telnet
