Metadata-Version: 1.1
Name: dubbo-telnet
Version: 1.0.1b3
Summary: Dubbo Telnet Client of python
Home-page: https://github.com/WALL-E/dubbo-telnet-py
Author: zhangzheng
Author-email: zhangzheng@qianbao.com
License: unlicense
Download-URL: https://github.com/WALL-E/dubbo-telnet-py/raw/master/dist/dubbo_telnet-1.0.1b3-py2.7.egg
Keywords: dubbo,dubbo_telnet,telnet,
Platform: UNKNOWN
Classifier: Development Status :: 4 - Beta
Classifier: Environment :: Console
Classifier: Intended Audience :: Developers
Classifier: License :: OSI Approved :: MIT License
Classifier: Operating System :: MacOS
Classifier: Operating System :: POSIX
Classifier: Operating System :: POSIX :: Linux
Classifier: Programming Language :: Python :: 2.6
Classifier: Programming Language :: Python :: 2.7
Classifier: Programming Language :: Python :: 3
Classifier: Topic :: Software Development :: Libraries :: Python Modules
Classifier: Topic :: Communications
Classifier: Topic :: System :: Networking
Classifier: Topic :: Software Development :: Libraries :: Java Libraries
